chilmesh/CHILmesh.py
chilmesh/__init__.py
chilmesh/utils/plot_utils.py
chilmesh-0.1.0.dist-info/licenses/LICENSE
chilmesh-0.1.0.dist-info/METADATA
chilmesh-0.1.0.dist-info/WHEEL
chilmesh-0.1.0.dist-info/top_level.txt
chilmesh-0.1.0.dist-info/RECORD
