Metadata-Version: 2.4
Name: chilmesh
Version: 0.1.0
Summary: Advanced mesh generation and smoothing for hydrodynamic domains
Author: Dominik Mattioli
License: MIT License
Requires-Python: >=3.8
License-File: LICENSE
Requires-Dist: numpy
Requires-Dist: matplotlib
Requires-Dist: scipy
Dynamic: license-file
